setup.cfg
setup.py
endiciapy/__init__.py
endiciapy/endicia.py
endiciapy/enums.py
endiciapy/response.py
endiciapy/serialization.py
endiciapy/xml_to_dict.py
endiciapy.egg-info/PKG-INFO
endiciapy.egg-info/SOURCES.txt
endiciapy.egg-info/dependency_links.txt
endiciapy.egg-info/entry_points.txt
endiciapy.egg-info/not-zip-safe
endiciapy.egg-info/top_level.txt