Metadata-Version: 1.0
Name: endiciapy
Version: 0.0dev
Summary: Python wrapper for Endicia Label Server Application Programming Interface (API)
Home-page: https://github.com/troolee/endiciapy
Author: mauriciosl
Author-email: mauriciosl@yahoo.com.br
License: UNKNOWN
Keywords: endicia label api
Platform: UNKNOWN
